thermal_sim/__init__.py
thermal_sim/thermal_sim.py
thermal_sim-1.0.dist-info/METADATA
thermal_sim-1.0.dist-info/WHEEL
thermal_sim-1.0.dist-info/top_level.txt
thermal_sim-1.0.dist-info/RECORD
