Metadata-Version: 2.1
Name: thermal_sim
Version: 1.0
Summary: Create thermal system based on componennts, automatically calculates differetial equations based on connections and simulates using a variety of solvers.
Author-email: Isak Åslund <aslundisak@gmail.com>
Project-URL: Homepage, https://github.com/elixir7/thermal_sim_py
Project-URL: Issues, https://github.com/elixir7/thermal_sim_py/issues
Classifier: Programming Language :: Python :: 3
Classifier: License :: OSI Approved :: MIT License
Classifier: Operating System :: OS Independent
Requires-Python: >=3.8
